{"vocabulary_size":22303,"word_count":14430,"word_frequency_count":{"imp":30,"mpo":30,"por":60,"ort":60,"lay":91,"ayo":91,"you":91,"out":91,"ftl":60,"as":60,"ass":30,"ssi":30,"sig":30,"ign":30,"res":270,"esu":210,"sul":210,"ult":240,"lts":120,"{":120,"tit":150,"itl":150,"tle":150,"exa":60,"xam":60,"amp":60,"mpl":60,"ple":60,"des":60,"esc":60,"scr":60,"cri":60,"rip":90,"ipt":60,"pti":60,"tio":90,"ion":120,"lor":31,"ore":30,"rem":30,"ips":30,"psu":30,"sum":30,"dol":30,"olo":30,"sit":30,"ame":90,"met":240,"ped":30,"ede":30,"id":30,"pel":30,"ell":30,"lle":30,"len":30,"ent":210,"nte":120,"tes":30,"esq":30,"squ":30,"que":30,"sol":30,"oll":30,"lli":30,"lic":30,"ici":30,"cit":30,"itu":30,"tud":30,"udi":30,"din":30,"tur":30,"urp":30,"rpi":30,"pis":30,"sed":32,"in":30,"lib":30,"ibe":30,"ber":30,"ero":30,"dic":30,"ict":30,"ctu":30,"tum":30,"}":30,"pag":120,"age":120,"fre":90,"ree":90,"eem":90,"ema":90,"mar":90,"ark":90,"rke":90,"ker":90,"if":60,"siz":30,"ize":30,"the":30,"her":30,"ere":31,"wer":30,"no":60,"els":30,"lse":30,"ul":60,"lis":60,"ist":60,"li":60,"str":91,"tro":31,"ron":31,"ong":31,"{re":60,"le}":60,"p":61,"on}":60,"thi":60,"his":60,"is":60,"a":30,"com":120,"omm":30,"mme":30,"men":30,"cur":60,"urr":60,"rre":60,"ren":60,"ntt":60,"tti":60,"tim":60,"ime":60,"mac":240,"acr":240,"cro":240,"now":30,"tri":60,"rin":30,"ing":60,"ful":30,"ull":30,"ll}":30,"tex":30,"ext":30,"tru":30,"rue":30,"doc":30,"oct":30,"cty":30,"typ":30,"ype":30,"htm":90,"tml":90,"lan":31,"ang":31,"ng}":30,"hea":60,"ead":60,"{ti":30,"eta":210,"tat":60,"ata":60,"tag":90,"ags":90,"bod":60,"ody":60,"nes":30,"est":30,"ste":30,"ted":30,"foo":60,"oot":60,"ote":60,"ter":60,"def":30,"efa":30,"fau":30,"aul":30,"omp":90,"mpr":60,"pre":60,"ess":60,"cha":30,"har":30,"ars":30,"rse":30,"set":30,"utf":30,"htt":30,"ttp":30,"equ":30,"qui":30,"uiv":30,"x":30,"ua":30,"mpa":30,"pat":30,"ati":30,"tib":30,"ibl":30,"ble":30,"con":90,"ont":90,"ten":90,"ie":30,"edg":30,"dge":30,"nam":60,"vie":30,"iew":30,"ewp":30,"wpo":30,"wid":31,"idt":31,"dth":31,"dev":30,"evi":30,"vic":30,"ice":30,"ini":30,"nit":30,"iti":30,"tia":30,"ial":30,"sca":30,"cal":30,"ale":30,"for":30,"orm":30,"rma":30,"mat":30,"det":30,"ete":30,"tec":30,"ect":30,"cti":30,"tel":30,"ele":30,"lep":30,"eph":30,"pho":30,"hon":30,"one":30,"usi":30,"sin":30,"v":30,"ver":30,"ers":30,"rsi":30,"sio":30}}