{"vocabulary_size":22303,"word_count":1578960,"word_frequency_count":{"mod":3240,"odu":2190,"dul":2160,"ule":2160,"con":990,"onn":390,"pon":390,"onc":390,"nch":390,"cho":390,"sin":90,"inb":90,"nbo":90,"bor":90,"ord":90,"rde":150,"lay":55290,"aye":55200,"yer":55200,"f":43531,"cu":31770,"ted":2100,"edi":2100,"dit":2100,"dc":270,"tag":1440,"ags":1440,"fp":22710,"tex":10800,"ext":10860,"ref":2430,"efe":2160,"fer":2250,"ere":2280,"ren":2160,"enc":2190,"nce":2640,"xa":5670,"at":25890,"sil":26460,"ilk":26460,"lks":26340,"eff":9960,"ffe":9960,"fec":9960,"ect":12330,"cts":10020,"fon":10170,"ont":10980,"siz":23820,"ize":23820,"thi":10260,"hic":10110,"ick":10110,"ckn":10110,"kne":10110,"nes":10170,"ess":10110,"val":8340,"alu":2160,"lue":2160,"hid":930,"ide":930,"use":6540,"ser":6540,"gpi":540,"pio":540,"lcd":360,"rs":60,"spi":90,"sck":60,"mis":60,"iso":60,"txd":120,"mdi":60,"dio":180,"crs":60,"dv":30,"mdc":60,"tx":120,"en":120,"rxd":120,"v":360,"gnd":3270,"mos":60,"osi":210,"clk":180,"t":450,"c":2970,"nda":420,"wak":60,"ake":60,"keu":60,"eup":60,"col":60,"fil":240,"can":120,"td":60,"rd":60,"rx":60,"i":60,"scl":60,"sda":60,"vdd":90,"dda":60,"dac":60,"ch":180,"isp":60,"res":2130,"ese":150,"set":150,"cia":1110,"iaa":840,"p":840,"lin":12360,"ine":12300,"sta":31320,"tar":28950,"art":28950,"end":29580,"wid":30360,"idt":30360,"dth":30360,"pad":25740,"thr":9930,"hru":9780,"hol":9930,"ole":9930,"rec":1470,"dri":11010,"ril":11070,"ill":11250,"ers":13770,"mas":12900,"ask":12900,"ova":6180,"foo":330,"oot":420,"otp":390,"tpr":330,"pri":330,"rin":510,"int":330,"nts":540,"log":240,"ogo":240,"osh":120,"shw":120,"hwa":120,"d":4290,"b":14760,"g":390,"pol":480,"oly":480,"pts":480,"xy":13353,"daf":30,"aff":30,"kic":90,"ica":390,"cad":90,"pcb":271,"ver":510,"rsi":90,"sio":150,"ion":270,"hos":90,"ost":60,"cbn":60,"bne":60,"new":180,"bzr":30,"pro":240,"rod":30,"duc":270,"uct":30,"gen":90,"ene":60,"ner":330,"era":60,"ral":60,"ink":60,"nks":60,"no":150,"nne":150,"nec":750,"are":60,"rea":60,"dra":60,"raw":60,"awi":60,"win":60,"ing":330,"ngs":60,"tra":1080,"rac":630,"ack":360,"cks":120,"zon":1080,"one":870,"les":120,"net":34260,"ets":60,"pag":90,"age":330,"a":2610,"sig":300,"ign":300,"gna":300,"nal":300,"adh":750,"dhe":120,"hes":120,"pas":2700,"ast":2760,"ste":2700,"dwg":60,"wgs":60,"cmt":60,"mts":60,"eco":120,"edg":450,"dge":540,"cut":180,"uts":180,"mar":240,"arg":210,"rgi":180,"gin":300,"crt":4980,"rty":4980,"tyd":4980,"fab":1950,"etu":90,"tup":90,"las":150,"ace":450,"cle":6390,"lea":660,"ear":480,"ara":540,"ran":660,"anc":480,"onl":60,"nly":60,"min":390,"seg":16230,"egm":16170,"gme":16170,"men":16650,"ent":17340,"via":1560,"uvi":480,"ias":180,"all":390,"llo":180,"low":300,"owe":120,"wed":120,"to":780,"aux":120,"axi":1440,"xis":60,"ori":930,"rig":120,"igi":120,"vis":150,"isi":120,"sib":120,"ibl":120,"ble":120,"ele":240,"lem":60,"eme":60,"fff":30,"ffc":30,"fcf":60,"cff":30,"cbp":60,"bpl":60,"plo":300,"lot":300,"tpa":60,"par":60,"ram":120,"ams":60,"rse":60,"sel":120,"lec":120,"cti":120,"tio":120,"x":450,"ege":60,"ger":60,"erb":60,"rbe":60,"ber":120,"rex":60,"xte":60,"ten":120,"ens":120,"nsi":300,"ons":2910,"fal":630,"als":660,"lse":630,"exc":60,"xcl":60,"clu":60,"lud":60,"ude":60,"dee":60,"eed":120,"gel":60,"ela":60,"tru":150,"rue":150,"ewi":120,"otf":60,"tfr":60,"fra":60,"ame":420,"mer":120,"aso":60,"son":120,"onm":60,"nma":60,"ode":900,"sea":60,"eau":60,"uxo":60,"xor":60,"hpg":240,"pgl":240,"glp":240,"lpe":240,"pen":240,"enn":60,"nnu":60,"num":60,"umb":60,"mbe":60,"nsp":60,"spe":60,"pee":60,"ndi":60,"dia":360,"iam":180,"met":180,"ete":240,"ter":840,"eno":60,"nov":60,"ove":60,"erl":60,"rla":60,"psn":60,"sne":60,"neg":60,"ega":60,"gat":60,"ati":60,"tiv":60,"ive":60,"psa":60,"out":270,"utp":180,"tpu":180,"put":180,"otr":60,"tre":60,"otv":60,"tva":60,"oti":60,"tin":180,"inv":60,"nvi":60,"let":60,"ads":330,"dso":60,"sub":60,"ubt":60,"btr":60,"act":60,"ctm":60,"tma":60,"skf":60,"kfr":60,"fro":60,"rom":120,"oms":60,"msi":60,"utf":60,"tfo":60,"for":90,"orm":90,"rma":180,"mat":90,"mir":150,"irr":150,"rro":690,"ror":150,"lls":60,"lsh":60,"sha":720,"hap":690,"ape":720,"sca":900,"cal":1200,"ale":900,"utd":60,"tdi":60,"dir":60,"ire":60,"cto":690,"tor":3750,"ory":60,"pdf":450,"dfs":30,"bat":180,"att":450,"swd":120,"wdi":120,"swc":120,"wcl":120,"led":2010,"u":3870,"adc":390,"add":4680,"adg":450,"ade":930,"adf":450,"ada":360,"adb":270,"adj":540,"ant":240,"cla":91,"ass":181,"def":61,"efa":61,"fau":61,"aul":61,"ult":61,"his":60,"is":60,"the":180,"cap":750,"apa":750,"pac":990,"aci":750,"cit":750,"ito":750,"ors":540,"smd":3900,"tst":12780,"tam":12780,"amp":12780,"des":1380,"esc":1380,"scr":1380,"efl":180,"flo":180,"sol":300,"old":930,"lde":840,"der":780,"eri":300,"avx":150,"see":360,"smc":150,"mcc":150,"ccp":150,"pat":1680,"ath":1680,"ttr":210,"del":840,"wrl":840,"xyz":2520,"rot":840,"ota":840,"tat":990,"ate":960,"e":1920,"n":180,"dd":180,"cka":240,"kag":240,"ges":240,"ba":570,"cir":5910,"irc":5910,"rcl":5910,"cen":690,"nte":660,"pin":601,"hea":481,"ead":661,"str":270,"rai":270,"aig":240,"igh":240,"ght":240,"hro":150,"rou":480,"oug":150,"ugh":150,"bb":90,"esi":2070,"sis":2250,"ist":2250,"sto":2250,"r":1560,"cc":30,"ish":30,"hay":30,"dcr":30,"crc":30,"rcw":30,"cry":210,"rys":60,"yst":60,"tal":870,"osc":30,"sci":30,"cil":30,"lla":30,"lat":90,"ato":30,"cx":30,"db":180,"fed":30,"ede":30,"ded":570,"nrf":120,"wlc":30,"lcs":30,"csp":30,"dad":30,"cea":30,"eaa":30,"h":270,"j":210,"dsh":630,"pes":630,"ghz":60,"bal":60,"cf":150,"ffd":60,"fdd":60,"fef":60,"atu":150,"tus":150,"nam":150,"hat":90,"atc":90,"tch":270,"yes":120,"arc":750,"her":91,"erm":91,"mal":361,"gap":90,"bri":90,"rid":90,"idg":90,"smo":90,"moo":90,"oth":90,"hin":90,"cha":90,"ham":90,"amf":90,"mfe":90,"rad":90,"adi":90,"diu":90,"ius":90,"lyg":120,"ygo":120,"gon":120,"lle":30,"kee":60,"eep":180,"epo":60,"pou":61,"cop":60,"opp":60,"ppe":60,"per":270,"erp":60,"rpo":60,"our":60,"not":60,"mol":540,"nar":570,"arr":540,"row":540,"mm":2910,"nxp":270,"sot":540,"po":180,"sc":181,"pa":180,"ans":180,"q":1500,"bc":330,"ang":780,"ngl":780,"gle":780,"tht":300,"ayo":30,"you":30,"xts":30,"tsi":30,"xtl":30,"tli":30,"com":420,"omm":360,"mme":420,"aro":30,"oun":330,"und":330,"tit":120,"itl":150,"tle":120,"blo":60,"loc":60,"ock":60,"ltc":150,"tco":210,"cor":271,"orn":271,"rne":271,"rbc":30,"bco":90,"rep":270,"epe":390,"pea":270,"eat":270,"inc":271,"ncr":271,"crx":150,"tbt":510,"bte":510,"pos":510,"lbc":61,"jus":180,"ust":300,"sti":270,"tif":180,"ify":180,"rtc":61,"dat":120,"k":600,"rev":60,"bol":90,"lef":30,"eft":30,"z":30,"pap":30,"id":31,"s":30,"she":60,"hee":60,"eet":60,"ile":30,"y":30,"omp":60,"mpa":60,"pan":60,"any":60,"fid":240,"idu":240,"uci":240,"ial":1620,"pwr":60,"jum":60,"ump":60,"mpe":60,"dis":210,"isc":180,"pit":180,"itc":180,"nf":60,"ghh":30,"hho":30,"ea":60,"ert":300,"rti":300,"tic":480,"eds":150,"~":30,"~ub":30,"ubu":30,"bun":30,"unt":30,"ntu":30,"por":30,"ort":30,"rtr":30,"ait":30,"jue":90,"ueg":90,"ego":90,"sim":1470,"imo":1470,"mon":1470,"edu":90,"roy":30,"oye":30,"yec":30,"jua":60,"uan":60,"agu":90,"gus":90,"bas":90,"ssi":90,"ise":30,"señ":30,"eño":30,"ces":30,"lic":30,"ice":30,"nci":30,"bsd":30,"ef":60,"but":1440,"utt":1440,"tto":1440,"ton":1440,"btn":1440,"cfg":720,"aac":600,"aco":600,"pwm":120,"vcc":540,"nsh":1350,"shi":1350,"hie":1350,"iel":1350,"eld":1350,"mag":180,"agn":180,"gne":180,"eti":180,"icb":120,"cbu":120,"buz":240,"uzz":240,"zze":240,"zer":240,"ros":120,"abt":180,"rc":180,"lek":60,"ekt":60,"ktr":60,"tro":60,"oma":60,"bee":120,"sum":60,"umm":60,"sw":810,"pus":540,"ush":540,"sma":270,"dca":30,"ed":180,"dbf":60,"bff":30,"dbd":30,"bdd":30,"bd":90,"dbb":30,"bbb":30,"xia":1380,"din":240,"l":120,"hor":810,"riz":810,"izo":810,"nta":810,"rie":120,"ies":120,"w":1262,"len":120,"eng":120,"ngt":120,"gth":120,"htt":60,"ttp":60,"cdn":60,"rei":60,"eic":60,"ich":60,"che":60,"hel":60,"elt":60,"de":300,"doc":60,"ocu":60,"cum":60,"ume":60,"enb":60,"nbl":60,"bla":60,"yag":60,"ohm":60,"rm":1710,"fe":150,"bce":30,"aec":30,"ff":120,"cb":30,"dbc":30,"be":120,"erd":60,"roj":60,"ojo":60,"azu":60,"zul":60,"ama":60,"ari":60,"{ki":30,"kip":30,"ipr":30,"prj":30,"rjm":30,"jmo":30,"od}":30,"cef":30,"efc":30,"gr":750,"aut":60,"uto":60,"git":32,"tla":30,"lab":30,"aba":30,"gam":30,"ski":30,"kil":30,"df":120,"bes":30,"est":30,"tec":120,"da":120,"jmp":30,"ind":30,"ndu":30,"dus":30,"tri":30,"ria":30,"rge":30,"nti":30,"ina":30,"ce":180,"cd":60,"nag":30,"ec":60,"eb":60,"aa":30,"ee":90,"ad":60,"ab":30,"bca":30,"af":90,"fd":30,"dcd":30,"ae":30,"eda":30,"daa":30,"aad":30,"fc":90,"fb":30,"fa":30,"bde":30,"ac":60,"deb":30,"cfd":30,"ceb":30,"bf":30,"cba":30}}